{
  "timestamp": "2026-07-16T18:35:54.164578+00:00",
  "house": {
    "indoor_temp": null,
    "indoor_humidity": null,
    "outdoor_temp": null,
    "outdoor_humidity": null,
    "wind_speed": null,
    "wind_direction": null,
    "pressure": null,
    "rain_today": null,
    "uv_index": null,
    "power_usage": null,
    "gas_consumption": null,
    "heating_active": null
  },
  "locations": {
    "altrincham": {
      "temp": 28.0,
      "conditions": "Sunny",
      "forecast": [
        {
          "date": "2026-07-16",
          "max": 28.0,
          "min": 12.0
        },
        {
          "date": "2026-07-17",
          "max": 28.0,
          "min": 13.0
        },
        {
          "date": "2026-07-18",
          "max": 23.0,
          "min": 12.0
        }
      ]
    },
    "overseal": {
      "temp": 27.0,
      "conditions": "Sunny",
      "forecast": [
        {
          "date": "2026-07-16",
          "max": 28.0,
          "min": 11.0
        },
        {
          "date": "2026-07-17",
          "max": 29.0,
          "min": 11.0
        },
        {
          "date": "2026-07-18",
          "max": 26.0,
          "min": 10.0
        }
      ]
    },
    "llandudno": {
      "temp": 23.0,
      "conditions": "Sunny",
      "forecast": [
        {
          "date": "2026-07-16",
          "max": 22.0,
          "min": 13.0
        },
        {
          "date": "2026-07-17",
          "max": 20.0,
          "min": 13.0
        },
        {
          "date": "2026-07-18",
          "max": 17.0,
          "min": 12.0
        }
      ]
    }
  },
  "astronomy": {
    "sunrise": "05:01 AM",
    "sunset": "09:29 PM",
    "moon_phase": "Waxing Crescent",
    "moon_illumination": "4",
    "moonrise": "07:33 AM",
    "moonset": "10:39 PM"
  },
  "metrolink": null,
  "headlines": [
    "EU forces Google to share its toys with the other AI and search kids",
    "AI vendors have found someone to pay their infrastructure bills: You",
    "Kick your mouse out of the house with this AI-assisted keyboard utility",
    "C'mon, just copy this text string and paste it into your macOS Terminal – it'll fix your computer, honest"
  ],
  "crew_quote": "\"Blimey, with it being twenty-eight degrees out there, I reckon I could fry an egg on my curry! Who needs a sunny holiday when you've got space and a good takeaway?\""
}