{
  "timestamp": "2026-06-23T09:45:57.972614+00:00",
  "house": {
    "indoor_temp": 24.4,
    "indoor_humidity": 57.0,
    "outdoor_temp": 25.8,
    "outdoor_humidity": 70.0,
    "wind_speed": 0.0,
    "wind_direction": 52.0,
    "pressure": 1021.7,
    "rain_today": 0.0,
    "uv_index": 1.0,
    "power_usage": 334.0,
    "gas_consumption": 124.247028492917,
    "heating_active": false
  },
  "locations": {
    "altrincham": {
      "temp": 24.0,
      "conditions": "Sunny",
      "forecast": [
        {
          "date": "2026-06-23",
          "max": 30.0,
          "min": 16.0
        },
        {
          "date": "2026-06-24",
          "max": 32.0,
          "min": 17.0
        },
        {
          "date": "2026-06-25",
          "max": 31.0,
          "min": 19.0
        }
      ]
    },
    "overseal": {
      "temp": 19.0,
      "conditions": "Sunny",
      "forecast": [
        {
          "date": "2026-06-23",
          "max": 31.0,
          "min": 14.0
        },
        {
          "date": "2026-06-24",
          "max": 31.0,
          "min": 19.0
        },
        {
          "date": "2026-06-25",
          "max": 31.0,
          "min": 16.0
        }
      ]
    },
    "llandudno": {
      "temp": 22.0,
      "conditions": "Partly cloudy",
      "forecast": [
        {
          "date": "2026-06-23",
          "max": 23.0,
          "min": 15.0
        },
        {
          "date": "2026-06-24",
          "max": 23.0,
          "min": 14.0
        },
        {
          "date": "2026-06-25",
          "max": 28.0,
          "min": 18.0
        }
      ]
    }
  },
  "astronomy": {
    "sunrise": "04:41 AM",
    "sunset": "09:42 PM",
    "moon_phase": "Waxing Gibbous",
    "moon_illumination": "61",
    "moonrise": "03:24 PM",
    "moonset": "01:03 AM"
  },
  "metrolink": "Weather Warning - Take care when you travel stay hydrated and allow more time for your journey",
  "headlines": [
    "Datacenters dip a toe back into waterborne computing despite obvious challenges",
    "Digital indigestion: Fizzy Coca-Cola display chokes on full storage",
    "Five Eyes spooks warn AI means infosec incidents can become ‘major operational and financial crises’",
    "India and China are home to 2.9 billion people – and together they bought just 13 million PCs in Q1"
  ],
  "crew_quote": "\"Ah, the weather's just brilliant! Perfect for sitting in a sunny spot with a cold curry and pretending I’m not sweating like a pig!\""
}